pygattpi/__init__.py
pygattpi/device.py
pygattpi/exceptions.py
pygattpi/util.py
pygattpi/backends/__init__.py
pygattpi/backends/backend.py
pygattpi/backends/bgapi/__init__.py
pygattpi/backends/bgapi/bgapi.py
pygattpi/backends/bgapi/bglib.py
pygattpi/backends/bgapi/constants.py
pygattpi/backends/bgapi/device.py
pygattpi/backends/bgapi/error_codes.py
pygattpi/backends/bgapi/exceptions.py
pygattpi/backends/bgapi/packets.py
pygattpi/backends/bgapi/util.py
pygattpi/backends/gatttool/__init__.py
pygattpi/backends/gatttool/device.py
pygattpi/backends/gatttool/gatttool.py
pygattpi-1.1.7.dist-info/LICENSE
pygattpi-1.1.7.dist-info/METADATA
pygattpi-1.1.7.dist-info/WHEEL
pygattpi-1.1.7.dist-info/top_level.txt
pygattpi-1.1.7.dist-info/RECORD
