Metadata-Version: 2.1
Name: pygattpi
Version: 1.1.7
Summary: Python Bluetooth LE (Low Energy) and GATT Library, forked from peplin/pygatt
Home-page: https://github.com/lemarquois/pygatt
Author: Markus Proeller <markus.proeller@pieye.org>
Author-email: markus.proeller@pieye.org
License: Apache 2.0 and MIT
Platform: UNKNOWN
Classifier: Intended Audience :: Developers
Classifier: License :: OSI Approved :: Apache Software License
Classifier: License :: OSI Approved :: MIT License
Classifier: Programming Language :: Python
Classifier: Programming Language :: Python :: 2.7
Classifier: Programming Language :: Python :: 3
Requires-Dist: pyserial
Requires-Dist: enum-compat
Provides-Extra: gatttool
Requires-Dist: pexpect ; extra == 'gatttool'
